itertools_len/__init__.py
itertools_len/py.typed
itertools_len-1.3.dist-info/METADATA
itertools_len-1.3.dist-info/WHEEL
itertools_len-1.3.dist-info/licenses/LICENSE
itertools_len-1.3.dist-info/RECORD
