Metadata-Version: 2.4
Name: itertools-len
Version: 1.3
Project-URL: Source, https://github.com/flying-sheep/itertools-len
Project-URL: Documentation, https://itertools-len.readthedocs.io/
Author-email: "Philipp A." <flying-sheep@web.de>
License-Expression: GPL-3.0-or-later
License-File: LICENSE
Classifier: Development Status :: 5 - Production/Stable
Classifier: Intended Audience :: Developers
Classifier: Programming Language :: Python :: 3
Classifier: Typing :: Typed
Requires-Python: >=3.11
Provides-Extra: docs
Requires-Dist: furo; extra == 'docs'
Requires-Dist: sphinx; extra == 'docs'
Provides-Extra: speedups
Requires-Dist: scipy; extra == 'speedups'
Provides-Extra: test
Requires-Dist: pytest; extra == 'test'
Requires-Dist: pytest-cov; extra == 'test'
